[
  {"level": "easy", "text": "用 10 秒钟做一个搞怪自拍表情，给大家看。"},
  {"level": "easy", "text": "学三种不同动物的叫声，各叫一声。"},
  {"level": "easy", "text": "用夸张播音腔说：「欢迎收看 PartyGame 真心话大冒险！」"},
  {"level": "easy", "text": "单脚站立 20 秒，期间不能笑场。"},
  {"level": "easy", "text": "即兴跳 15 秒「广场舞」风格舞蹈。"},
  {"level": "easy", "text": "用家乡话或方言说一句「我准备好了」。"},
  {"level": "easy", "text": "和右边的人击掌，并大声夸对方一句。"},
  {"level": "easy", "text": "做 10 个开合跳，边跳边报数。"},
  {"level": "easy", "text": "模仿一种你熟悉的电影角色，让大家猜。"},
  {"level": "easy", "text": "用唱歌的方式说出你的昵称或名字。"},
  {"level": "easy", "text": "闭眼原地转 5 圈，然后走直线走三步。"},
  {"level": "easy", "text": "用三种语气说「好的」，分别是开心、委屈、严肃。"},
  {"level": "easy", "text": "给大家表演「手机没电了」的崩溃瞬间。"},
  {"level": "easy", "text": "用屁股写一个大写的「好」字（空中写字即可）。"},
  {"level": "easy", "text": "选一位朋友，认真地说一句土味情话。"},

  {"level": "normal", "text": "即兴清唱 20 秒，歌词内容不限。"},
  {"level": "normal", "text": "模仿在场一位朋友的招牌动作（友善版，不得冒犯）。"},
  {"level": "normal", "text": "用「新闻播报」格式介绍自己：姓名、籍贯、今日状态。"},
  {"level": "normal", "text": "和左边的人玩石头剪刀布，输的人要说一句互相夸夸的话。"},
  {"level": "normal", "text": "做 15 秒「慢动作跑步」，表情要到位。"},
  {"level": "normal", "text": "用英语（或其他外语）介绍你最喜欢的一道菜。"},
  {"level": "normal", "text": "即兴来一段 20 秒的「产品推销」，对象可以是任意物品。"},
  {"level": "normal", "text": "给大家表演「第一次约会紧张」的样子。"},
  {"level": "normal", "text": "选一首歌，只唱副歌部分，可以跑调。"},
  {"level": "normal", "text": "用三种不同身份（如老师、网红、导游）各说一句话。"},
  {"level": "normal", "text": "和在场所有人逐一碰拳，并说「辛苦了」。"},
  {"level": "normal", "text": "表演「吃到超级辣食物」的反应，持续 10 秒。"},
  {"level": "normal", "text": "用 Rap 风格夸一下 PartyGame 这个游戏。"},
  {"level": "normal", "text": "做 10 个俯卧撑；做不到则改为 20 次深蹲。"},
  {"level": "normal", "text": "选一位朋友，两人对视 10 秒，先笑的人要再夸对方一句。"},

  {"level": "bold", "text": "发一条友善动态（文字内容由大家现场指定，不得含隐私或攻击性内容）。"},
  {"level": "bold", "text": "给通讯录里最近联系的一个人发「今晚聚会超开心」——可先给大家过目再发。"},
  {"level": "bold", "text": "用「主持人宣布获奖」的方式，公开夸在场一位朋友 30 秒。"},
  {"level": "bold", "text": "即兴表演「向喜欢的人表白」，对象可以是虚构的。"},
  {"level": "bold", "text": "和一位朋友合影，摆一个你们都觉得最沙雕的姿势。"},
  {"level": "bold", "text": "用「分手台词」的 dramatic 语气，念一段搞笑文案（由大家提供一句）。"},
  {"level": "bold", "text": "现场学一位朋友的口头禅，连说三遍。"},
  {"level": "bold", "text": "给大家展示你相册里最近一张非自拍照片，并讲背后的故事。"},
  {"level": "bold", "text": "选两位朋友，各说一句你欣赏他们的理由。"},
  {"level": "bold", "text": "用「颁奖典礼」口吻，给自己颁一个搞笑奖项并致词。"},
  {"level": "bold", "text": "表演「接到好消息」和「接到坏消息」两种反应，各 10 秒。"},
  {"level": "bold", "text": "和右边的人交换一件小物品（钥匙扣、纸巾等）直到游戏结束。"},
  {"level": "bold", "text": "用「带货直播」风格介绍你旁边的人 20 秒。"},
  {"level": "bold", "text": "现场编一个 30 秒的微型脱口秀，主题：聚会糗事。"},
  {"level": "bold", "text": "给大家表演「假装自己是 AI 助手」回答三个问题。"}
]
